bertserini/__init__.py
bertserini/interactive.py
bertserini/experiments/__init__.py
bertserini/experiments/args.py
bertserini/experiments/evaluate.py
bertserini/experiments/inference.py
bertserini/reader/__init__.py
bertserini/reader/base.py
bertserini/reader/bert_reader.py
bertserini/retriever/__init__.py
bertserini/retriever/pyserini_retriever.py
bertserini/train/__init__.py
bertserini/train/run_squad.py
bertserini/utils/__init__.py
bertserini/utils/utils.py
bertserini/utils/utils_new.py
bertserini/utils/utils_squad.py
bertserini-0.0.2.post2.dist-info/LICENSE
bertserini-0.0.2.post2.dist-info/METADATA
bertserini-0.0.2.post2.dist-info/WHEEL
bertserini-0.0.2.post2.dist-info/top_level.txt
bertserini-0.0.2.post2.dist-info/RECORD
